.gitignore
HELP.md
LICENSE.txt
MANIFEST.in
README.md
README.rst
setup.py
diclipy/__init__.py
diclipy/diclipy.py
diclipy/ui.json
diclipy.egg-info/PKG-INFO
diclipy.egg-info/SOURCES.txt
diclipy.egg-info/dependency_links.txt
diclipy.egg-info/entry_points.txt
diclipy.egg-info/requires.txt
diclipy.egg-info/top_level.txt
diclipy/__pycache__/__init__.cpython-34.pyc
diclipy/__pycache__/diclipy.cpython-34.pyc