Metadata-Version: 2.1
Name: diclipy
Version: 0.1.6
Summary: CLI script for posting/reading/commenting on Diaspora* pod written around Diaspy API
Home-page: https://notabug.org/uzver/diclipy
Author: uzver
Author-email: uzver@protonmail.ch
License: GNU/GPLv3+
Keywords: diaspora diaspy cli social blog federative network fediverse
Platform: UNKNOWN
Classifier: Development Status :: 2 - Pre-Alpha
Classifier: License :: OSI Approved :: GNU General Public License v3 or later (GPLv3+)
Classifier: Programming Language :: Python
Classifier: Programming Language :: Python :: 3.6
Classifier: Topic :: Internet
Classifier: Topic :: Utilities
License-File: LICENSE.txt
